upymenu/__init__.py
upymenu-0.0.1.dist-info/LICENSE
upymenu-0.0.1.dist-info/METADATA
upymenu-0.0.1.dist-info/WHEEL
upymenu-0.0.1.dist-info/top_level.txt
upymenu-0.0.1.dist-info/RECORD
