Metadata-Version: 2.1
Name: upymenu
Version: 0.0.1
Summary: A micropython Menu for LCD Displays
Home-page: https://github.com/jplattel/upymenu
Author: Joost Plattel
License: UNKNOWN
Platform: UNKNOWN
